job_scraper/__init__.py
job_scraper/sources/jora.py
job_scraper/sources/kalibrr.py
job_scraper/types.py
job_scraper/utils.py
phjob_scraper-0.1.2.dist-info/METADATA
phjob_scraper-0.1.2.dist-info/WHEEL
phjob_scraper-0.1.2.dist-info/RECORD
